{"estPropertyType":"2","result":[{"data":[{"estPropertyType":"2","saleableFloorArea":"374 / 35","discountRate":"43","month":"02","transPrice":"300,000","aplySysId":"1321347387467","floor":"L","type":"A","plan":"3039","pricePerArea":"803 / 8,646"},{"estPropertyType":"2","saleableFloorArea":"385 / 36","discountRate":"43","month":"12","transPrice":"620,000","aplySysId":"1321347387467","floor":"L","type":"A","plan":"3039","pricePerArea":"1,609 / 17,318"},{"estPropertyType":"2","saleableFloorArea":"385 / 36","discountRate":"43","month":"07","transPrice":"550,000","aplySysId":"1321347387467","floor":"M","type":"A","plan":"3039","pricePerArea":"1,427 / 15,363"},{"estPropertyType":"2","saleableFloorArea":"385 / 36","discountRate":"43","month":"02","transPrice":"628,000","aplySysId":"1321347387467","floor":"H","type":"A","plan":"3039","pricePerArea":"1,630 / 17,542"},{"estPropertyType":"2","saleableFloorArea":"407 / 38","discountRate":"43","month":"11","transPrice":"682,000","aplySysId":"1321347387467","floor":"M","type":"A","plan":"3039","pricePerArea":"1,676 / 18,042"},{"estPropertyType":"2","saleableFloorArea":"407 / 38","discountRate":"43","month":"06","transPrice":"698,000","aplySysId":"1321347387467","floor":"M","type":"A","plan":"3039","pricePerArea":"1,715 / 18,466"},{"estPropertyType":"2","saleableFloorArea":"407 / 38","discountRate":"43","month":"11","transPrice":"730,000","aplySysId":"1321347387467","floor":"H","type":"A","plan":"3039","pricePerArea":"1,794 / 19,312"},{"estPropertyType":"2","saleableFloorArea":"407 / 38","discountRate":"43","month":"05","transPrice":"720,000","aplySysId":"1321347387467","floor":"H","type":"A","plan":"3039","pricePerArea":"1,770 / 19,048"},{"estPropertyType":"2","saleableFloorArea":"443 / 41","discountRate":"43","month":"05","transPrice":"712,000","aplySysId":"1321347387467","floor":"H","type":"A","plan":"3039","pricePerArea":"1,605 / 17,282"},{"estPropertyType":"2","saleableFloorArea":"443 / 41","discountRate":"43","month":"04","transPrice":"850,000","aplySysId":"1321347387467","floor":"M","type":"A","plan":"3039","pricePerArea":"1,917 / 20,631"},{"estPropertyType":"2","saleableFloorArea":"544 / 51","discountRate":"43","month":"01","transPrice":"1,000,000","aplySysId":"1321347387467","floor":"H","type":"A","plan":"3039","pricePerArea":"1,840 / 19,802"},{"estPropertyType":"2","saleableFloorArea":"544 / 51","discountRate":"43","month":"02","transPrice":"930,000","aplySysId":"1321347387467","floor":"L","type":"A","plan":"3039","pricePerArea":"1,711 / 18,416"},{"estPropertyType":"2","saleableFloorArea":"598 / 56","discountRate":"43","month":"10","transPrice":"1,050,000","aplySysId":"1321347387467","floor":"H","type":"A","plan":"3039","pricePerArea":"1,754 / 18,885"}],"year":"2002"},{"data":[{"estPropertyType":"2","saleableFloorArea":"376 / 35","discountRate":"43","month":"12","transPrice":"650,000","aplySysId":"1321347387467","floor":"L","type":"A","plan":"3039","pricePerArea":"1,730 / 18,625"},{"estPropertyType":"2","saleableFloorArea":"376 / 35","discountRate":"45","month":"05","transPrice":"700,000","aplySysId":"1321347387467","floor":"H","type":"A","plan":"3039","pricePerArea":"1,863 / 20,057"},{"estPropertyType":"2","saleableFloorArea":"376 / 35","discountRate":"43","month":"05","transPrice":"726,000","aplySysId":"1321347387467","floor":"H","type":"A","plan":"3039","pricePerArea":"1,933 / 20,802"},{"estPropertyType":"2","saleableFloorArea":"407 / 38","discountRate":"43","month":"05","transPrice":"828,000","aplySysId":"1321347387467","floor":"L","type":"A","plan":"3039","pricePerArea":"2,035 / 21,905"},{"estPropertyType":"2","saleableFloorArea":"598 / 56","discountRate":"43","month":"07","transPrice":"1,238,000","aplySysId":"1321347387467","floor":"L","type":"A","plan":"3039","pricePerArea":"2,069 / 22,266"},{"estPropertyType":"2","saleableFloorArea":"598 / 56","discountRate":"43","month":"11","transPrice":"1,438,000","aplySysId":"1321347387467","floor":"H","type":"A","plan":"3039","pricePerArea":"2,403 / 25,863"},{"estPropertyType":"2","saleableFloorArea":"598 / 56","discountRate":"43","month":"10","transPrice":"1,350,000","aplySysId":"1321347387467","floor":"M","type":"A","plan":"3039","pricePerArea":"2,256 / 24,281"}],"year":"2007"},{"data":[{"estPropertyType":"2","saleableFloorArea":"376 / 35","discountRate":"43","month":"03","transPrice":"2,650,000","aplySysId":"1321347387467","floor":"H","type":"A","plan":"3039","pricePerArea":"7,054 / 75,931"},{"estPropertyType":"2","saleableFloorArea":"376 / 35","discountRate":"43","month":"08","transPrice":"2,580,000","aplySysId":"1321347387467","floor":"M","type":"A","plan":"3039","pricePerArea":"6,868 / 73,926"},{"estPropertyType":"2","saleableFloorArea":"385 / 36","discountRate":"43","month":"09","transPrice":"2,820,000","aplySysId":"1321347387467","floor":"H","type":"A","plan":"3039","pricePerArea":"7,318 / 78,771"},{"estPropertyType":"2","saleableFloorArea":"407 / 38","discountRate":"43","month":"12","transPrice":"2,880,000","aplySysId":"1321347387467","floor":"L","type":"A","plan":"3039","pricePerArea":"7,078 / 76,190"},{"estPropertyType":"2","saleableFloorArea":"407 / 38","discountRate":"43","month":"12","transPrice":"3,150,000","aplySysId":"1321347387467","floor":"M","type":"A","plan":"3039","pricePerArea":"7,742 / 83,333"},{"estPropertyType":"2","saleableFloorArea":"598 / 56","discountRate":"43","month":"09","transPrice":"5,780,000","aplySysId":"1321347387467","floor":"H","type":"A","plan":"3039","pricePerArea":"9,658 / 103,957"}],"year":"2017"},{"data":[{"estPropertyType":"2","saleableFloorArea":"376 / 35","discountRate":"45","month":"12","transPrice":"2,598,000","aplySysId":"1321347387467","floor":"L","type":"A","plan":"3039","pricePerArea":"6,916 / 74,441"},{"estPropertyType":"2","saleableFloorArea":"385 / 36","discountRate":"40","month":"05","transPrice":"2,200,000","aplySysId":"1321347387467","floor":"M","type":"A","plan":"3039","pricePerArea":"5,709 / 61,453"},{"estPropertyType":"2","saleableFloorArea":"385 / 36","discountRate":"43","month":"07","transPrice":"2,448,000","aplySysId":"1321347387467","floor":"H","type":"A","plan":"3039","pricePerArea":"6,353 / 68,380"},{"estPropertyType":"2","saleableFloorArea":"407 / 38","discountRate":"43","month":"02","transPrice":"2,606,000","aplySysId":"1321347387467","floor":"M","type":"A","plan":"3039","pricePerArea":"6,405 / 68,942"},{"estPropertyType":"2","saleableFloorArea":"407 / 38","discountRate":"43","month":"04","transPrice":"2,480,000","aplySysId":"1321347387467","floor":"L","type":"A","plan":"3039","pricePerArea":"6,095 / 65,608"},{"estPropertyType":"2","saleableFloorArea":"441 / 41","discountRate":"43","month":"03","transPrice":"2,110,000","aplySysId":"1321347387467","floor":"L","type":"A","plan":"3039","pricePerArea":"4,781 / 51,463"},{"estPropertyType":"2","saleableFloorArea":"544 / 51","discountRate":"43","month":"03","transPrice":"3,610,000","aplySysId":"1321347387467","floor":"M","type":"A","plan":"3039","pricePerArea":"6,641 / 71,485"}],"year":"2016"},{"data":[{"estPropertyType":"2","saleableFloorArea":"376 / 35","discountRate":"43","month":"01","transPrice":"1,930,000","aplySysId":"1321347387467","floor":"M","type":"A","plan":"3039","pricePerArea":"5,138 / 55,301"},{"estPropertyType":"2","saleableFloorArea":"385 / 36","discountRate":"43","month":"03","transPrice":"2,150,000","aplySysId":"1321347387467","floor":"H","type":"A","plan":"3039","pricePerArea":"5,579 / 60,056"},{"estPropertyType":"2","saleableFloorArea":"407 / 38","discountRate":"43","month":"08","transPrice":"2,280,000","aplySysId":"1321347387467","floor":"L","type":"A","plan":"3039","pricePerArea":"5,604 / 60,317"},{"estPropertyType":"2","saleableFloorArea":"407 / 38","discountRate":"43","month":"02","transPrice":"2,000,000","aplySysId":"1321347387467","floor":"M","type":"A","plan":"3039","pricePerArea":"4,915 / 52,910"},{"estPropertyType":"2","saleableFloorArea":"443 / 41","discountRate":"43","month":"05","transPrice":"2,200,000","aplySysId":"1321347387467","floor":"L","type":"A","plan":"3039","pricePerArea":"4,961 / 53,398"},{"estPropertyType":"2","saleableFloorArea":"443 / 41","discountRate":"43","month":"04","transPrice":"2,200,000","aplySysId":"1321347387467","floor":"M","type":"A","plan":"3039","pricePerArea":"4,961 / 53,398"},{"estPropertyType":"2","saleableFloorArea":"443 / 41","discountRate":"43","month":"06","transPrice":"2,180,000","aplySysId":"1321347387467","floor":"M","type":"A","plan":"3039","pricePerArea":"4,916 / 52,913"},{"estPropertyType":"2","saleableFloorArea":"443 / 41","discountRate":"45","month":"12","transPrice":"2,750,000","aplySysId":"1321347387467","floor":"H","type":"A","plan":"3039","pricePerArea":"6,201 / 66,748"},{"estPropertyType":"2","saleableFloorArea":"544 / 51","discountRate":"43","month":"02","transPrice":"2,680,000","aplySysId":"1321347387467","floor":"L","type":"A","plan":"3039","pricePerArea":"4,930 / 53,069"},{"estPropertyType":"2","saleableFloorArea":"598 / 56","discountRate":"43","month":"06","transPrice":"3,138,000","aplySysId":"1321347387467","floor":"M","type":"A","plan":"3039","pricePerArea":"5,243 / 56,439"}],"year":"2014"},{"data":[{"estPropertyType":"2","saleableFloorArea":"376 / 35","discountRate":"40","month":"06","transPrice":"570,000","aplySysId":"1321347387467","floor":"H","type":"A","plan":"3039","pricePerArea":"1,517 / 16,332"},{"estPropertyType":"2","saleableFloorArea":"385 / 36","discountRate":"43","month":"03","transPrice":"500,000","aplySysId":"1321347387467","floor":"L","type":"A","plan":"3039","pricePerArea":"1,298 / 13,966"},{"estPropertyType":"2","saleableFloorArea":"385 / 36","discountRate":"43","month":"10","transPrice":"570,000","aplySysId":"1321347387467","floor":"L","type":"A","plan":"3039","pricePerArea":"1,479 / 15,922"},{"estPropertyType":"2","saleableFloorArea":"385 / 36","discountRate":"42","month":"09","transPrice":"700,000","aplySysId":"1321347387467","floor":"M","type":"A","plan":"3039","pricePerArea":"1,817 / 19,553"},{"estPropertyType":"2","saleableFloorArea":"385 / 36","discountRate":"43","month":"08","transPrice":"660,000","aplySysId":"1321347387467","floor":"M","type":"A","plan":"3039","pricePerArea":"1,713 / 18,436"},{"estPropertyType":"2","saleableFloorArea":"407 / 38","discountRate":"43","month":"06","transPrice":"695,000","aplySysId":"1321347387467","floor":"H","type":"A","plan":"3039","pricePerArea":"1,708 / 18,386"},{"estPropertyType":"2","saleableFloorArea":"407 / 38","discountRate":"43","month":"03","transPrice":"630,000","aplySysId":"1321347387467","floor":"M","type":"A","plan":"3039","pricePerArea":"1,548 / 16,667"},{"estPropertyType":"2","saleableFloorArea":"407 / 38","discountRate":"43","month":"10","transPrice":"730,000","aplySysId":"1321347387467","floor":"H","type":"A","plan":"3039","pricePerArea":"1,794 / 19,312"},{"estPropertyType":"2","saleableFloorArea":"441 / 41","discountRate":"43","month":"08","transPrice":"600,000","aplySysId":"1321347387467","floor":"L","type":"A","plan":"3039","pricePerArea":"1,360 / 14,634"},{"estPropertyType":"2","saleableFloorArea":"443 / 41","discountRate":"43","month":"05","transPrice":"780,000","aplySysId":"1321347387467","floor":"H","type":"A","plan":"3039","pricePerArea":"1,759 / 18,932"},{"estPropertyType":"2","saleableFloorArea":"443 / 41","discountRate":"43","month":"04","transPrice":"733,000","aplySysId":"1321347387467","floor":"H","type":"A","plan":"3039","pricePerArea":"1,653 / 17,791"},{"estPropertyType":"2","saleableFloorArea":"544 / 51","discountRate":"43","month":"02","transPrice":"628,000","aplySysId":"1321347387467","floor":"L","type":"A","plan":"3039","pricePerArea":"1,155 / 12,436"},{"estPropertyType":"2","saleableFloorArea":"598 / 56","discountRate":"43","month":"09","transPrice":"1,120,000","aplySysId":"1321347387467","floor":"M","type":"A","plan":"3039","pricePerArea":"1,871 / 20,144"},{"estPropertyType":"2","saleableFloorArea":"598 / 56","discountRate":"43","month":"10","transPrice":"1,250,000","aplySysId":"1321347387467","floor":"M","type":"A","plan":"3039","pricePerArea":"2,089 / 22,482"}],"year":"2004"},{"data":[{"estPropertyType":"2","saleableFloorArea":"376 / 35","discountRate":"43","month":"07","transPrice":"1,950,000","aplySysId":"1321347387467","floor":"H","type":"A","plan":"3039","pricePerArea":"5,191 / 55,874"},{"estPropertyType":"2","saleableFloorArea":"407 / 38","discountRate":"41","month":"06","transPrice":"1,980,000","aplySysId":"1321347387467","floor":"L","type":"A","plan":"3039","pricePerArea":"4,866 / 52,381"},{"estPropertyType":"2","saleableFloorArea":"598 / 56","discountRate":"43","month":"07","transPrice":"3,198,000","aplySysId":"1321347387467","floor":"M","type":"A","plan":"3039","pricePerArea":"5,344 / 57,518"}],"year":"2013"},{"data":[{"estPropertyType":"2","saleableFloorArea":"385 / 36","discountRate":"43","month":"05","transPrice":"1,250,000","aplySysId":"1321347387467","floor":"H","type":"A","plan":"3039","pricePerArea":"3,244 / 34,916"},{"estPropertyType":"2","saleableFloorArea":"407 / 38","discountRate":"43","month":"06","transPrice":"1,290,000","aplySysId":"1321347387467","floor":"M","type":"A","plan":"3039","pricePerArea":"3,170 / 34,127"},{"estPropertyType":"2","saleableFloorArea":"441 / 41","discountRate":"43","month":"03","transPrice":"780,000","aplySysId":"1321347387467","floor":"L","type":"A","plan":"3039","pricePerArea":"1,767 / 19,024"},{"estPropertyType":"2","saleableFloorArea":"544 / 51","discountRate":"43","month":"06","transPrice":"1,260,000","aplySysId":"1321347387467","floor":"L","type":"A","plan":"3039","pricePerArea":"2,318 / 24,950"},{"estPropertyType":"2","saleableFloorArea":"544 / 51","discountRate":"43","month":"06","transPrice":"1,680,000","aplySysId":"1321347387467","floor":"H","type":"A","plan":"3039","pricePerArea":"3,091 / 33,267"},{"estPropertyType":"2","saleableFloorArea":"598 / 56","discountRate":"43","month":"04","transPrice":"1,760,000","aplySysId":"1321347387467","floor":"M","type":"A","plan":"3039","pricePerArea":"2,941 / 31,655"}],"year":"2010"},{"data":[{"estPropertyType":"2","saleableFloorArea":"385 / 36","discountRate":"43","month":"03","transPrice":"3,670,000","aplySysId":"1321347387467","floor":"M","type":"A","plan":"3039","pricePerArea":"9,524 / 102,514"},{"estPropertyType":"2","saleableFloorArea":"407 / 38","discountRate":"43","month":"06","transPrice":"3,080,000","aplySysId":"1321347387467","floor":"L","type":"A","plan":"3039","pricePerArea":"7,570 / 81,481"}],"year":"2021"},{"data":[{"estPropertyType":"2","saleableFloorArea":"407 / 38","discountRate":"43","month":"06","transPrice":"3,560,000","aplySysId":"1321347387467","floor":"H","type":"A","plan":"3039","pricePerArea":"8,750 / 94,180"},{"estPropertyType":"2","saleableFloorArea":"544 / 51","discountRate":"43","month":"11","transPrice":"4,608,000","aplySysId":"1321347387467","floor":"L","type":"A","plan":"3039","pricePerArea":"8,477 / 91,248"},{"estPropertyType":"2","saleableFloorArea":"544 / 51","discountRate":"43","month":"02","transPrice":"4,330,000","aplySysId":"1321347387467","floor":"H","type":"A","plan":"3039","pricePerArea":"7,966 / 85,743"}],"year":"2019"},{"data":[{"estPropertyType":"2","saleableFloorArea":"407 / 38","discountRate":"43","month":"05","transPrice":"838,000","aplySysId":"1321347387467","floor":"L","type":"A","plan":"3039","pricePerArea":"2,060 / 22,169"}],"year":"2005"},{"data":[{"estPropertyType":"2","saleableFloorArea":"443 / 41","discountRate":"43","month":"12","transPrice":"620,000","aplySysId":"1321347387467","floor":"M","type":"A","plan":"3039","pricePerArea":"1,398 / 15,049"},{"estPropertyType":"2","saleableFloorArea":"443 / 41","discountRate":"43","month":"02","transPrice":"720,000","aplySysId":"1321347387467","floor":"H","type":"A","plan":"3039","pricePerArea":"1,624 / 17,476"},{"estPropertyType":"2","saleableFloorArea":"443 / 41","discountRate":"43","month":"11","transPrice":"580,000","aplySysId":"1321347387467","floor":"M","type":"A","plan":"3039","pricePerArea":"1,308 / 14,078"},{"estPropertyType":"2","saleableFloorArea":"598 / 56","discountRate":"43","month":"04","transPrice":"910,000","aplySysId":"1321347387467","floor":"H","type":"A","plan":"3039","pricePerArea":"1,521 / 16,367"},{"estPropertyType":"2","saleableFloorArea":"598 / 56","discountRate":"43","month":"01","transPrice":"955,000","aplySysId":"1321347387467","floor":"L","type":"A","plan":"3039","pricePerArea":"1,596 / 17,176"}],"year":"2003"},{"data":[{"estPropertyType":"2","saleableFloorArea":"443 / 41","discountRate":"43","month":"04","transPrice":"3,650,000","aplySysId":"1321347387467","floor":"M","type":"A","plan":"3039","pricePerArea":"8,230 / 88,592"},{"estPropertyType":"2","saleableFloorArea":"544 / 51","discountRate":"43","month":"02","transPrice":"4,110,000","aplySysId":"1321347387467","floor":"M","type":"A","plan":"3039","pricePerArea":"7,561 / 81,386"},{"estPropertyType":"2","saleableFloorArea":"598 / 56","discountRate":"43","month":"04","transPrice":"5,050,000","aplySysId":"1321347387467","floor":"H","type":"A","plan":"3039","pricePerArea":"8,438 / 90,827"}],"year":"2020"},{"data":[{"estPropertyType":"2","saleableFloorArea":"443 / 41","discountRate":"43","month":"10","transPrice":"1,730,000","aplySysId":"1321347387467","floor":"L","type":"A","plan":"3039","pricePerArea":"3,901 / 41,990"}],"year":"2012"},{"data":[{"estPropertyType":"2","saleableFloorArea":"443 / 41","discountRate":"43","month":"09","transPrice":"1,100,000","aplySysId":"1321347387467","floor":"H","type":"A","plan":"3039","pricePerArea":"2,480 / 26,699"}],"year":"2009"},{"data":[{"estPropertyType":"2","saleableFloorArea":"443 / 41","discountRate":"45","month":"03","transPrice":"865,000","aplySysId":"1321347387467","floor":"M","type":"A","plan":"3039","pricePerArea":"1,950 / 20,995"}],"year":"2006"},{"data":[{"estPropertyType":"2","saleableFloorArea":"544 / 51","discountRate":"43","month":"03","transPrice":"4,398,000","aplySysId":"1321347387467","floor":"M","type":"A","plan":"3039","pricePerArea":"8,091 / 87,089"}],"year":"2018"},{"data":[{"estPropertyType":"2","saleableFloorArea":"544 / 51","discountRate":"43","month":"08","transPrice":"1,150,000","aplySysId":"1321347387467","floor":"L","type":"A","plan":"3039","pricePerArea":"2,116 / 22,772"}],"year":"2008"},{"data":[{"estPropertyType":"2","saleableFloorArea":"544 / 51","discountRate":"43","month":"10","transPrice":"2,200,000","aplySysId":"1321347387467","floor":"H","type":"A","plan":"3039","pricePerArea":"4,047 / 43,564"}],"year":"2011"}],"courtAndEstate":{"zh-Hans":"凤钻苑","zh-Hant":"鳳鑽苑","en":"Fung Chuen Court"},"district":{"zh-Hans":"黄大仙","zh-Hant":"黃大仙","en":"Wong Tai Sin"},"location":{"zh-Hans":"钻石山","zh-Hant":"鑽石山","en":"Diamond Hill"},"aplySysId":"1321347387467","region":{"zh-Hans":"九龙","zh-Hant":"九龍","en":"Kowloon"}}