{"estPropertyType":"2","result":[{"data":[{"estPropertyType":"2","saleableFloorArea":"433 / 40","discountRate":"42","month":"12","transPrice":"2,500,000","aplySysId":"1321347387575","floor":"H","type":"A","plan":"3133","pricePerArea":"5,778 / 62,189"},{"estPropertyType":"2","saleableFloorArea":"433 / 40","discountRate":"38","month":"12","transPrice":"2,225,000","aplySysId":"1321347387575","floor":"H","type":"A","plan":"3133","pricePerArea":"5,142 / 55,348"},{"estPropertyType":"2","saleableFloorArea":"438 / 41","discountRate":"44","month":"12","transPrice":"2,398,000","aplySysId":"1321347387575","floor":"M","type":"A","plan":"3133","pricePerArea":"5,474 / 58,919"},{"estPropertyType":"2","saleableFloorArea":"546 / 51","discountRate":"38","month":"04","transPrice":"1,968,000","aplySysId":"1321347387575","floor":"M","type":"A","plan":"3133","pricePerArea":"3,606 / 38,817"},{"estPropertyType":"2","saleableFloorArea":"546 / 51","discountRate":"38","month":"05","transPrice":"1,930,000","aplySysId":"1321347387575","floor":"L","type":"A","plan":"3133","pricePerArea":"3,537 / 38,067"},{"estPropertyType":"2","saleableFloorArea":"546 / 51","discountRate":"41","month":"03","transPrice":"2,238,000","aplySysId":"1321347387575","floor":"M","type":"A","plan":"3133","pricePerArea":"4,101 / 44,142"},{"estPropertyType":"2","saleableFloorArea":"598 / 56","discountRate":"38","month":"12","transPrice":"3,275,000","aplySysId":"1321347387575","floor":"H","type":"A","plan":"3133","pricePerArea":"5,472 / 58,903"},{"estPropertyType":"2","saleableFloorArea":"598 / 56","discountRate":"41","month":"03","transPrice":"2,620,000","aplySysId":"1321347387575","floor":"H","type":"A","plan":"3133","pricePerArea":"4,378 / 47,122"},{"estPropertyType":"2","saleableFloorArea":"598 / 56","discountRate":"38","month":"03","transPrice":"2,399,900","aplySysId":"1321347387575","floor":"H","type":"A","plan":"3133","pricePerArea":"4,010 / 43,164"},{"estPropertyType":"2","saleableFloorArea":"603 / 56","discountRate":"41","month":"03","transPrice":"2,450,000","aplySysId":"1321347387575","floor":"M","type":"A","plan":"3133","pricePerArea":"4,064 / 43,750"},{"estPropertyType":"2","saleableFloorArea":"606 / 56","discountRate":"41","month":"04","transPrice":"2,180,000","aplySysId":"1321347387575","floor":"L","type":"A","plan":"3133","pricePerArea":"3,597 / 38,721"},{"estPropertyType":"2","saleableFloorArea":"606 / 56","discountRate":"38","month":"04","transPrice":"2,250,000","aplySysId":"1321347387575","floor":"M","type":"A","plan":"3133","pricePerArea":"3,713 / 39,964"},{"estPropertyType":"2","saleableFloorArea":"606 / 56","discountRate":"38","month":"08","transPrice":"2,860,000","aplySysId":"1321347387575","floor":"M","type":"A","plan":"3133","pricePerArea":"4,719 / 50,799"},{"estPropertyType":"2","saleableFloorArea":"640 / 60","discountRate":"38","month":"04","transPrice":"2,650,000","aplySysId":"1321347387575","floor":"H","type":"A","plan":"3133","pricePerArea":"4,138 / 44,538"},{"estPropertyType":"2","saleableFloorArea":"645 / 60","discountRate":"21","month":"11","transPrice":"3,000,000","aplySysId":"1321347387575","floor":"M","type":"A","plan":"3133","pricePerArea":"4,653 / 50,083"}],"year":"2012"},{"data":[{"estPropertyType":"2","saleableFloorArea":"433 / 40","discountRate":"38","month":"11","transPrice":"658,000","aplySysId":"1321347387575","floor":"H","type":"A","plan":"3133","pricePerArea":"1,521 / 16,368"},{"estPropertyType":"2","saleableFloorArea":"433 / 40","discountRate":"41","month":"08","transPrice":"730,000","aplySysId":"1321347387575","floor":"H","type":"A","plan":"3133","pricePerArea":"1,687 / 18,159"},{"estPropertyType":"2","saleableFloorArea":"433 / 40","discountRate":"38","month":"07","transPrice":"640,000","aplySysId":"1321347387575","floor":"H","type":"A","plan":"3133","pricePerArea":"1,479 / 15,920"},{"estPropertyType":"2","saleableFloorArea":"433 / 40","discountRate":"41","month":"09","transPrice":"630,000","aplySysId":"1321347387575","floor":"H","type":"A","plan":"3133","pricePerArea":"1,456 / 15,672"},{"estPropertyType":"2","saleableFloorArea":"433 / 40","discountRate":"38","month":"08","transPrice":"500,000","aplySysId":"1321347387575","floor":"H","type":"A","plan":"3133","pricePerArea":"1,156 / 12,438"},{"estPropertyType":"2","saleableFloorArea":"433 / 40","discountRate":"38","month":"10","transPrice":"610,000","aplySysId":"1321347387575","floor":"H","type":"A","plan":"3133","pricePerArea":"1,410 / 15,174"},{"estPropertyType":"2","saleableFloorArea":"435 / 40","discountRate":"38","month":"04","transPrice":"550,000","aplySysId":"1321347387575","floor":"M","type":"A","plan":"3133","pricePerArea":"1,265 / 13,614"},{"estPropertyType":"2","saleableFloorArea":"438 / 41","discountRate":"44","month":"11","transPrice":"480,000","aplySysId":"1321347387575","floor":"M","type":"A","plan":"3133","pricePerArea":"1,096 / 11,794"},{"estPropertyType":"2","saleableFloorArea":"538 / 50","discountRate":"38","month":"12","transPrice":"910,000","aplySysId":"1321347387575","floor":"H","type":"A","plan":"3133","pricePerArea":"1,691 / 18,200"},{"estPropertyType":"2","saleableFloorArea":"538 / 50","discountRate":"41","month":"04","transPrice":"815,000","aplySysId":"1321347387575","floor":"H","type":"A","plan":"3133","pricePerArea":"1,514 / 16,300"},{"estPropertyType":"2","saleableFloorArea":"538 / 50","discountRate":"38","month":"01","transPrice":"990,000","aplySysId":"1321347387575","floor":"H","type":"A","plan":"3133","pricePerArea":"1,839 / 19,800"},{"estPropertyType":"2","saleableFloorArea":"538 / 50","discountRate":"38","month":"01","transPrice":"723,000","aplySysId":"1321347387575","floor":"H","type":"A","plan":"3133","pricePerArea":"1,343 / 14,460"},{"estPropertyType":"2","saleableFloorArea":"538 / 50","discountRate":"38","month":"09","transPrice":"838,000","aplySysId":"1321347387575","floor":"H","type":"A","plan":"3133","pricePerArea":"1,557 / 16,760"},{"estPropertyType":"2","saleableFloorArea":"541 / 50","discountRate":"38","month":"04","transPrice":"810,000","aplySysId":"1321347387575","floor":"M","type":"A","plan":"3133","pricePerArea":"1,496 / 16,103"},{"estPropertyType":"2","saleableFloorArea":"541 / 50","discountRate":"38","month":"12","transPrice":"880,000","aplySysId":"1321347387575","floor":"M","type":"A","plan":"3133","pricePerArea":"1,625 / 17,495"},{"estPropertyType":"2","saleableFloorArea":"546 / 51","discountRate":"38","month":"06","transPrice":"750,000","aplySysId":"1321347387575","floor":"L","type":"A","plan":"3133","pricePerArea":"1,374 / 14,793"},{"estPropertyType":"2","saleableFloorArea":"546 / 51","discountRate":"38","month":"03","transPrice":"830,000","aplySysId":"1321347387575","floor":"L","type":"A","plan":"3133","pricePerArea":"1,521 / 16,371"},{"estPropertyType":"2","saleableFloorArea":"546 / 51","discountRate":"38","month":"09","transPrice":"695,000","aplySysId":"1321347387575","floor":"L","type":"A","plan":"3133","pricePerArea":"1,274 / 13,708"},{"estPropertyType":"2","saleableFloorArea":"546 / 51","discountRate":"38","month":"07","transPrice":"750,000","aplySysId":"1321347387575","floor":"L","type":"A","plan":"3133","pricePerArea":"1,374 / 14,793"},{"estPropertyType":"2","saleableFloorArea":"598 / 56","discountRate":"41","month":"01","transPrice":"935,000","aplySysId":"1321347387575","floor":"H","type":"A","plan":"3133","pricePerArea":"1,562 / 16,817"},{"estPropertyType":"2","saleableFloorArea":"598 / 56","discountRate":"38","month":"11","transPrice":"950,000","aplySysId":"1321347387575","floor":"H","type":"A","plan":"3133","pricePerArea":"1,587 / 17,086"},{"estPropertyType":"2","saleableFloorArea":"603 / 56","discountRate":"38","month":"04","transPrice":"990,000","aplySysId":"1321347387575","floor":"M","type":"A","plan":"3133","pricePerArea":"1,642 / 17,679"},{"estPropertyType":"2","saleableFloorArea":"603 / 56","discountRate":"41","month":"01","transPrice":"1,080,000","aplySysId":"1321347387575","floor":"M","type":"A","plan":"3133","pricePerArea":"1,792 / 19,286"},{"estPropertyType":"2","saleableFloorArea":"603 / 56","discountRate":"38","month":"04","transPrice":"910,000","aplySysId":"1321347387575","floor":"M","type":"A","plan":"3133","pricePerArea":"1,510 / 16,250"},{"estPropertyType":"2","saleableFloorArea":"606 / 56","discountRate":"38","month":"11","transPrice":"920,000","aplySysId":"1321347387575","floor":"M","type":"A","plan":"3133","pricePerArea":"1,518 / 16,341"},{"estPropertyType":"2","saleableFloorArea":"606 / 56","discountRate":"38","month":"03","transPrice":"786,000","aplySysId":"1321347387575","floor":"L","type":"A","plan":"3133","pricePerArea":"1,297 / 13,961"},{"estPropertyType":"2","saleableFloorArea":"606 / 56","discountRate":"38","month":"11","transPrice":"880,000","aplySysId":"1321347387575","floor":"L","type":"A","plan":"3133","pricePerArea":"1,452 / 15,631"},{"estPropertyType":"2","saleableFloorArea":"640 / 60","discountRate":"38","month":"01","transPrice":"890,000","aplySysId":"1321347387575","floor":"H","type":"A","plan":"3133","pricePerArea":"1,390 / 14,958"},{"estPropertyType":"2","saleableFloorArea":"649 / 60","discountRate":"38","month":"03","transPrice":"939,000","aplySysId":"1321347387575","floor":"M","type":"A","plan":"3133","pricePerArea":"1,447 / 15,572"}],"year":"2003"},{"data":[{"estPropertyType":"2","saleableFloorArea":"433 / 40","discountRate":"38","month":"06","transPrice":"760,000","aplySysId":"1321347387575","floor":"H","type":"A","plan":"3133","pricePerArea":"1,756 / 18,905"},{"estPropertyType":"2","saleableFloorArea":"435 / 40","discountRate":"41","month":"05","transPrice":"680,000","aplySysId":"1321347387575","floor":"M","type":"A","plan":"3133","pricePerArea":"1,564 / 16,832"},{"estPropertyType":"2","saleableFloorArea":"438 / 41","discountRate":"38","month":"11","transPrice":"750,000","aplySysId":"1321347387575","floor":"M","type":"A","plan":"3133","pricePerArea":"1,712 / 18,428"},{"estPropertyType":"2","saleableFloorArea":"438 / 41","discountRate":"38","month":"03","transPrice":"680,000","aplySysId":"1321347387575","floor":"L","type":"A","plan":"3133","pricePerArea":"1,552 / 16,708"},{"estPropertyType":"2","saleableFloorArea":"538 / 50","discountRate":"38","month":"12","transPrice":"1,105,000","aplySysId":"1321347387575","floor":"H","type":"A","plan":"3133","pricePerArea":"2,053 / 22,100"},{"estPropertyType":"2","saleableFloorArea":"538 / 50","discountRate":"41","month":"11","transPrice":"1,200,000","aplySysId":"1321347387575","floor":"H","type":"A","plan":"3133","pricePerArea":"2,230 / 24,000"},{"estPropertyType":"2","saleableFloorArea":"538 / 50","discountRate":"38","month":"04","transPrice":"980,000","aplySysId":"1321347387575","floor":"H","type":"A","plan":"3133","pricePerArea":"1,821 / 19,600"},{"estPropertyType":"2","saleableFloorArea":"538 / 50","discountRate":"38","month":"12","transPrice":"1,105,000","aplySysId":"1321347387575","floor":"H","type":"A","plan":"3133","pricePerArea":"2,053 / 22,100"},{"estPropertyType":"2","saleableFloorArea":"541 / 50","discountRate":"38","month":"09","transPrice":"980,000","aplySysId":"1321347387575","floor":"M","type":"A","plan":"3133","pricePerArea":"1,810 / 19,483"},{"estPropertyType":"2","saleableFloorArea":"541 / 50","discountRate":"41","month":"01","transPrice":"818,000","aplySysId":"1321347387575","floor":"M","type":"A","plan":"3133","pricePerArea":"1,511 / 16,262"},{"estPropertyType":"2","saleableFloorArea":"541 / 50","discountRate":"38","month":"04","transPrice":"1,050,000","aplySysId":"1321347387575","floor":"M","type":"A","plan":"3133","pricePerArea":"1,939 / 20,875"},{"estPropertyType":"2","saleableFloorArea":"546 / 51","discountRate":"41","month":"10","transPrice":"880,000","aplySysId":"1321347387575","floor":"L","type":"S","plan":"3133","pricePerArea":"1,613 / 17,357"},{"estPropertyType":"2","saleableFloorArea":"598 / 56","discountRate":"38","month":"01","transPrice":"990,000","aplySysId":"1321347387575","floor":"H","type":"A","plan":"3133","pricePerArea":"1,654 / 17,806"},{"estPropertyType":"2","saleableFloorArea":"603 / 56","discountRate":"41","month":"03","transPrice":"1,260,000","aplySysId":"1321347387575","floor":"M","type":"A","plan":"3133","pricePerArea":"2,090 / 22,500"},{"estPropertyType":"2","saleableFloorArea":"645 / 60","discountRate":"38","month":"04","transPrice":"1,060,000","aplySysId":"1321347387575","floor":"M","type":"A","plan":"3133","pricePerArea":"1,644 / 17,696"},{"estPropertyType":"2","saleableFloorArea":"645 / 60","discountRate":"38","month":"08","transPrice":"1,320,000","aplySysId":"1321347387575","floor":"M","type":"A","plan":"3133","pricePerArea":"2,047 / 22,037"},{"estPropertyType":"2","saleableFloorArea":"649 / 60","discountRate":"41","month":"09","transPrice":"970,000","aplySysId":"1321347387575","floor":"L","type":"A","plan":"3133","pricePerArea":"1,494 / 16,086"}],"year":"2004"},{"data":[{"estPropertyType":"2","saleableFloorArea":"433 / 40","discountRate":"38","month":"12","transPrice":"2,435,000","aplySysId":"1321347387575","floor":"H","type":"A","plan":"3133","pricePerArea":"5,627 / 60,572"},{"estPropertyType":"2","saleableFloorArea":"433 / 40","discountRate":"41","month":"07","transPrice":"2,668,000","aplySysId":"1321347387575","floor":"H","type":"A","plan":"3133","pricePerArea":"6,166 / 66,368"},{"estPropertyType":"2","saleableFloorArea":"433 / 40","discountRate":"44","month":"06","transPrice":"2,480,000","aplySysId":"1321347387575","floor":"H","type":"A","plan":"3133","pricePerArea":"5,731 / 61,692"},{"estPropertyType":"2","saleableFloorArea":"433 / 40","discountRate":"38","month":"12","transPrice":"2,730,000","aplySysId":"1321347387575","floor":"H","type":"A","plan":"3133","pricePerArea":"6,309 / 67,910"},{"estPropertyType":"2","saleableFloorArea":"538 / 50","discountRate":"41","month":"06","transPrice":"2,980,000","aplySysId":"1321347387575","floor":"H","type":"A","plan":"3133","pricePerArea":"5,537 / 59,600"},{"estPropertyType":"2","saleableFloorArea":"546 / 51","discountRate":"38","month":"06","transPrice":"2,468,000","aplySysId":"1321347387575","floor":"L","type":"A","plan":"3133","pricePerArea":"4,522 / 48,679"},{"estPropertyType":"2","saleableFloorArea":"546 / 51","discountRate":"45","month":"02","transPrice":"2,650,000","aplySysId":"1321347387575","floor":"L","type":"A","plan":"3133","pricePerArea":"4,856 / 52,268"},{"estPropertyType":"2","saleableFloorArea":"598 / 56","discountRate":"41","month":"05","transPrice":"3,680,000","aplySysId":"1321347387575","floor":"H","type":"A","plan":"3133","pricePerArea":"6,149 / 66,187"},{"estPropertyType":"2","saleableFloorArea":"598 / 56","discountRate":"38","month":"10","transPrice":"3,080,000","aplySysId":"1321347387575","floor":"H","type":"A","plan":"3133","pricePerArea":"5,146 / 55,396"},{"estPropertyType":"2","saleableFloorArea":"603 / 56","discountRate":"41","month":"08","transPrice":"3,260,000","aplySysId":"1321347387575","floor":"M","type":"A","plan":"3133","pricePerArea":"5,408 / 58,214"},{"estPropertyType":"2","saleableFloorArea":"606 / 56","discountRate":"41","month":"06","transPrice":"3,280,000","aplySysId":"1321347387575","floor":"M","type":"A","plan":"3133","pricePerArea":"5,412 / 58,259"},{"estPropertyType":"2","saleableFloorArea":"640 / 60","discountRate":"38","month":"01","transPrice":"3,600,000","aplySysId":"1321347387575","floor":"H","type":"A","plan":"3133","pricePerArea":"5,621 / 60,504"},{"estPropertyType":"2","saleableFloorArea":"645 / 60","discountRate":"38","month":"09","transPrice":"3,380,000","aplySysId":"1321347387575","floor":"M","type":"A","plan":"3133","pricePerArea":"5,242 / 56,427"}],"year":"2013"},{"data":[{"estPropertyType":"2","saleableFloorArea":"433 / 40","discountRate":"38","month":"05","transPrice":"3,920,000","aplySysId":"1321347387575","floor":"H","type":"A","plan":"3133","pricePerArea":"9,059 / 97,512"},{"estPropertyType":"2","saleableFloorArea":"438 / 41","discountRate":"38","month":"05","transPrice":"3,300,000","aplySysId":"1321347387575","floor":"M","type":"A","plan":"3133","pricePerArea":"7,533 / 81,081"},{"estPropertyType":"2","saleableFloorArea":"438 / 41","discountRate":"41","month":"11","transPrice":"3,680,000","aplySysId":"1321347387575","floor":"M","type":"A","plan":"3133","pricePerArea":"8,400 / 90,418"},{"estPropertyType":"2","saleableFloorArea":"546 / 51","discountRate":"38","month":"04","transPrice":"4,180,000","aplySysId":"1321347387575","floor":"L","type":"A","plan":"3133","pricePerArea":"7,659 / 82,446"},{"estPropertyType":"2","saleableFloorArea":"546 / 51","discountRate":"38","month":"06","transPrice":"4,350,000","aplySysId":"1321347387575","floor":"L","type":"A","plan":"3133","pricePerArea":"7,971 / 85,799"},{"estPropertyType":"2","saleableFloorArea":"598 / 56","discountRate":"41","month":"04","transPrice":"5,100,000","aplySysId":"1321347387575","floor":"H","type":"A","plan":"3133","pricePerArea":"8,522 / 91,727"},{"estPropertyType":"2","saleableFloorArea":"603 / 56","discountRate":"38","month":"09","transPrice":"4,750,000","aplySysId":"1321347387575","floor":"M","type":"A","plan":"3133","pricePerArea":"7,880 / 84,821"},{"estPropertyType":"2","saleableFloorArea":"603 / 56","discountRate":"38","month":"07","transPrice":"4,720,000","aplySysId":"1321347387575","floor":"M","type":"A","plan":"3133","pricePerArea":"7,830 / 84,286"},{"estPropertyType":"2","saleableFloorArea":"606 / 56","discountRate":"41","month":"06","transPrice":"5,400,000","aplySysId":"1321347387575","floor":"L","type":"S","plan":"3133","pricePerArea":"8,911 / 95,915"},{"estPropertyType":"2","saleableFloorArea":"606 / 56","discountRate":"38","month":"07","transPrice":"4,450,000","aplySysId":"1321347387575","floor":"L","type":"A","plan":"3133","pricePerArea":"7,343 / 79,041"},{"estPropertyType":"2","saleableFloorArea":"645 / 60","discountRate":"41","month":"03","transPrice":"5,100,000","aplySysId":"1321347387575","floor":"M","type":"A","plan":"3133","pricePerArea":"7,910 / 85,142"},{"estPropertyType":"2","saleableFloorArea":"645 / 60","discountRate":"38","month":"06","transPrice":"5,850,000","aplySysId":"1321347387575","floor":"M","type":"S","plan":"3133","pricePerArea":"9,073 / 97,663"},{"estPropertyType":"2","saleableFloorArea":"649 / 60","discountRate":"38","month":"01","transPrice":"4,820,000","aplySysId":"1321347387575","floor":"L","type":"A","plan":"3133","pricePerArea":"7,426 / 79,934"},{"estPropertyType":"2","saleableFloorArea":"649 / 60","discountRate":"38","month":"03","transPrice":"5,000,000","aplySysId":"1321347387575","floor":"L","type":"A","plan":"3133","pricePerArea":"7,703 / 82,919"},{"estPropertyType":"2","saleableFloorArea":"649 / 60","discountRate":"41","month":"09","transPrice":"5,410,000","aplySysId":"1321347387575","floor":"L","type":"A","plan":"3133","pricePerArea":"8,335 / 89,718"}],"year":"2020"},{"data":[{"estPropertyType":"2","saleableFloorArea":"433 / 40","discountRate":"33","month":"09","transPrice":"2,900,000","aplySysId":"1321347387575","floor":"H","type":"A","plan":"3133","pricePerArea":"6,702 / 72,139"},{"estPropertyType":"2","saleableFloorArea":"433 / 40","discountRate":"44","month":"02","transPrice":"3,050,000","aplySysId":"1321347387575","floor":"H","type":"A","plan":"3133","pricePerArea":"7,049 / 75,871"},{"estPropertyType":"2","saleableFloorArea":"433 / 40","discountRate":"38","month":"08","transPrice":"3,170,000","aplySysId":"1321347387575","floor":"H","type":"A","plan":"3133","pricePerArea":"7,326 / 78,856"},{"estPropertyType":"2","saleableFloorArea":"538 / 50","discountRate":"38","month":"04","transPrice":"3,400,000","aplySysId":"1321347387575","floor":"H","type":"A","plan":"3133","pricePerArea":"6,317 / 68,000"},{"estPropertyType":"2","saleableFloorArea":"538 / 50","discountRate":"41","month":"10","transPrice":"3,650,000","aplySysId":"1321347387575","floor":"H","type":"A","plan":"3133","pricePerArea":"6,782 / 73,000"},{"estPropertyType":"2","saleableFloorArea":"538 / 50","discountRate":"41","month":"05","transPrice":"3,360,000","aplySysId":"1321347387575","floor":"H","type":"A","plan":"3133","pricePerArea":"6,243 / 67,200"},{"estPropertyType":"2","saleableFloorArea":"541 / 50","discountRate":"41","month":"04","transPrice":"3,230,000","aplySysId":"1321347387575","floor":"M","type":"A","plan":"3133","pricePerArea":"5,966 / 64,215"},{"estPropertyType":"2","saleableFloorArea":"541 / 50","discountRate":"38","month":"06","transPrice":"3,938,000","aplySysId":"1321347387575","floor":"M","type":"A","plan":"3133","pricePerArea":"7,273 / 78,290"},{"estPropertyType":"2","saleableFloorArea":"598 / 56","discountRate":"38","month":"06","transPrice":"3,950,000","aplySysId":"1321347387575","floor":"H","type":"A","plan":"3133","pricePerArea":"6,600 / 71,043"},{"estPropertyType":"2","saleableFloorArea":"603 / 56","discountRate":"41","month":"06","transPrice":"3,570,000","aplySysId":"1321347387575","floor":"M","type":"A","plan":"3133","pricePerArea":"5,923 / 63,750"},{"estPropertyType":"2","saleableFloorArea":"606 / 56","discountRate":"38","month":"02","transPrice":"3,700,000","aplySysId":"1321347387575","floor":"L","type":"A","plan":"3133","pricePerArea":"6,105 / 65,719"},{"estPropertyType":"2","saleableFloorArea":"606 / 56","discountRate":"41","month":"08","transPrice":"3,900,000","aplySysId":"1321347387575","floor":"M","type":"A","plan":"3133","pricePerArea":"6,436 / 69,272"},{"estPropertyType":"2","saleableFloorArea":"606 / 56","discountRate":"38","month":"11","transPrice":"4,100,000","aplySysId":"1321347387575","floor":"L","type":"A","plan":"3133","pricePerArea":"6,766 / 72,824"}],"year":"2016"},{"data":[{"estPropertyType":"2","saleableFloorArea":"433 / 40","discountRate":"41","month":"11","transPrice":"3,600,000","aplySysId":"1321347387575","floor":"H","type":"A","plan":"3133","pricePerArea":"8,320 / 89,552"},{"estPropertyType":"2","saleableFloorArea":"433 / 40","discountRate":"41","month":"03","transPrice":"2,980,000","aplySysId":"1321347387575","floor":"H","type":"A","plan":"3133","pricePerArea":"6,887 / 74,129"},{"estPropertyType":"2","saleableFloorArea":"435 / 40","discountRate":"38","month":"05","transPrice":"3,180,000","aplySysId":"1321347387575","floor":"M","type":"A","plan":"3133","pricePerArea":"7,313 / 78,713"},{"estPropertyType":"2","saleableFloorArea":"435 / 40","discountRate":"41","month":"06","transPrice":"3,228,000","aplySysId":"1321347387575","floor":"M","type":"A","plan":"3133","pricePerArea":"7,423 / 79,901"},{"estPropertyType":"2","saleableFloorArea":"438 / 41","discountRate":"38","month":"07","transPrice":"3,300,000","aplySysId":"1321347387575","floor":"M","type":"A","plan":"3133","pricePerArea":"7,533 / 81,081"},{"estPropertyType":"2","saleableFloorArea":"438 / 41","discountRate":"38","month":"10","transPrice":"3,880,000","aplySysId":"1321347387575","floor":"L","type":"A","plan":"3133","pricePerArea":"8,857 / 95,332"},{"estPropertyType":"2","saleableFloorArea":"438 / 41","discountRate":"41","month":"09","transPrice":"3,580,000","aplySysId":"1321347387575","floor":"L","type":"A","plan":"3133","pricePerArea":"8,172 / 87,961"},{"estPropertyType":"2","saleableFloorArea":"438 / 41","discountRate":"38","month":"08","transPrice":"3,300,000","aplySysId":"1321347387575","floor":"L","type":"A","plan":"3133","pricePerArea":"7,533 / 81,081"},{"estPropertyType":"2","saleableFloorArea":"538 / 50","discountRate":"38","month":"04","transPrice":"4,200,000","aplySysId":"1321347387575","floor":"H","type":"A","plan":"3133","pricePerArea":"7,804 / 84,000"},{"estPropertyType":"2","saleableFloorArea":"541 / 50","discountRate":"41","month":"04","transPrice":"4,128,000","aplySysId":"1321347387575","floor":"M","type":"A","plan":"3133","pricePerArea":"7,624 / 82,068"},{"estPropertyType":"2","saleableFloorArea":"546 / 51","discountRate":"38","month":"12","transPrice":"4,380,000","aplySysId":"1321347387575","floor":"L","type":"A","plan":"3133","pricePerArea":"8,026 / 86,391"},{"estPropertyType":"2","saleableFloorArea":"598 / 56","discountRate":"38","month":"08","transPrice":"5,040,000","aplySysId":"1321347387575","floor":"H","type":"A","plan":"3133","pricePerArea":"8,421 / 90,647"},{"estPropertyType":"2","saleableFloorArea":"598 / 56","discountRate":"38","month":"07","transPrice":"5,380,000","aplySysId":"1321347387575","floor":"H","type":"A","plan":"3133","pricePerArea":"8,989 / 96,763"},{"estPropertyType":"2","saleableFloorArea":"606 / 56","discountRate":"38","month":"05","transPrice":"4,950,000","aplySysId":"1321347387575","floor":"M","type":"A","plan":"3133","pricePerArea":"8,168 / 87,922"},{"estPropertyType":"2","saleableFloorArea":"645 / 60","discountRate":"41","month":"07","transPrice":"4,680,000","aplySysId":"1321347387575","floor":"M","type":"A","plan":"3133","pricePerArea":"7,258 / 78,130"}],"year":"2017"},{"data":[{"estPropertyType":"2","saleableFloorArea":"433 / 40","discountRate":"41","month":"01","transPrice":"3,800,000","aplySysId":"1321347387575","floor":"H","type":"A","plan":"3133","pricePerArea":"8,782 / 94,527"},{"estPropertyType":"2","saleableFloorArea":"438 / 41","discountRate":"44","month":"05","transPrice":"3,320,000","aplySysId":"1321347387575","floor":"L","type":"A","plan":"3133","pricePerArea":"7,578 / 81,572"},{"estPropertyType":"2","saleableFloorArea":"538 / 50","discountRate":"41","month":"05","transPrice":"5,178,000","aplySysId":"1321347387575","floor":"H","type":"A","plan":"3133","pricePerArea":"9,621 / 103,560"},{"estPropertyType":"2","saleableFloorArea":"538 / 50","discountRate":"38","month":"03","transPrice":"4,280,000","aplySysId":"1321347387575","floor":"H","type":"S","plan":"3133","pricePerArea":"7,952 / 85,600"},{"estPropertyType":"2","saleableFloorArea":"538 / 50","discountRate":"38","month":"05","transPrice":"4,720,000","aplySysId":"1321347387575","floor":"H","type":"A","plan":"3133","pricePerArea":"8,770 / 94,400"},{"estPropertyType":"2","saleableFloorArea":"538 / 50","discountRate":"44","month":"04","transPrice":"4,680,000","aplySysId":"1321347387575","floor":"H","type":"A","plan":"3133","pricePerArea":"8,696 / 93,600"},{"estPropertyType":"2","saleableFloorArea":"606 / 56","discountRate":"41","month":"07","transPrice":"5,650,000","aplySysId":"1321347387575","floor":"L","type":"A","plan":"3133","pricePerArea":"9,323 / 100,355"},{"estPropertyType":"2","saleableFloorArea":"606 / 56","discountRate":"38","month":"04","transPrice":"4,820,000","aplySysId":"1321347387575","floor":"L","type":"A","plan":"3133","pricePerArea":"7,954 / 85,613"},{"estPropertyType":"2","saleableFloorArea":"649 / 60","discountRate":"44","month":"02","transPrice":"5,370,000","aplySysId":"1321347387575","floor":"L","type":"A","plan":"3133","pricePerArea":"8,273 / 89,055"}],"year":"2018"},{"data":[{"estPropertyType":"2","saleableFloorArea":"433 / 40","discountRate":"38","month":"06","transPrice":"3,715,000","aplySysId":"1321347387575","floor":"H","type":"A","plan":"3133","pricePerArea":"8,585 / 92,413"},{"estPropertyType":"2","saleableFloorArea":"538 / 50","discountRate":"41","month":"01","transPrice":"4,550,000","aplySysId":"1321347387575","floor":"H","type":"A","plan":"3133","pricePerArea":"8,454 / 91,000"},{"estPropertyType":"2","saleableFloorArea":"541 / 50","discountRate":"38","month":"03","transPrice":"4,398,000","aplySysId":"1321347387575","floor":"M","type":"A","plan":"3133","pricePerArea":"8,123 / 87,435"},{"estPropertyType":"2","saleableFloorArea":"546 / 51","discountRate":"38","month":"04","transPrice":"3,900,000","aplySysId":"1321347387575","floor":"M","type":"A","plan":"3133","pricePerArea":"7,146 / 76,923"},{"estPropertyType":"2","saleableFloorArea":"546 / 51","discountRate":"41","month":"01","transPrice":"4,160,000","aplySysId":"1321347387575","floor":"L","type":"A","plan":"3133","pricePerArea":"7,623 / 82,051"},{"estPropertyType":"2","saleableFloorArea":"546 / 51","discountRate":"38","month":"05","transPrice":"4,400,000","aplySysId":"1321347387575","floor":"L","type":"A","plan":"3133","pricePerArea":"8,063 / 86,785"},{"estPropertyType":"2","saleableFloorArea":"598 / 56","discountRate":"41","month":"06","transPrice":"5,000,000","aplySysId":"1321347387575","floor":"H","type":"A","plan":"3133","pricePerArea":"8,355 / 89,928"},{"estPropertyType":"2","saleableFloorArea":"603 / 56","discountRate":"38","month":"06","transPrice":"5,150,000","aplySysId":"1321347387575","floor":"M","type":"A","plan":"3133","pricePerArea":"8,544 / 91,964"},{"estPropertyType":"2","saleableFloorArea":"603 / 56","discountRate":"41","month":"03","transPrice":"4,480,000","aplySysId":"1321347387575","floor":"M","type":"A","plan":"3133","pricePerArea":"7,432 / 80,000"},{"estPropertyType":"2","saleableFloorArea":"606 / 56","discountRate":"41","month":"04","transPrice":"5,050,000","aplySysId":"1321347387575","floor":"L","type":"A","plan":"3133","pricePerArea":"8,333 / 89,698"},{"estPropertyType":"2","saleableFloorArea":"649 / 60","discountRate":"41","month":"05","transPrice":"5,360,000","aplySysId":"1321347387575","floor":"L","type":"A","plan":"3133","pricePerArea":"8,258 / 88,889"}],"year":"2021"},{"data":[{"estPropertyType":"2","saleableFloorArea":"433 / 40","discountRate":"41","month":"03","transPrice":"1,250,000","aplySysId":"1321347387575","floor":"H","type":"A","plan":"3133","pricePerArea":"2,889 / 31,095"},{"estPropertyType":"2","saleableFloorArea":"598 / 56","discountRate":"38","month":"01","transPrice":"1,350,000","aplySysId":"1321347387575","floor":"H","type":"A","plan":"3133","pricePerArea":"2,256 / 24,281"},{"estPropertyType":"2","saleableFloorArea":"606 / 56","discountRate":"41","month":"01","transPrice":"1,630,000","aplySysId":"1321347387575","floor":"L","type":"A","plan":"3133","pricePerArea":"2,690 / 28,952"},{"estPropertyType":"2","saleableFloorArea":"606 / 56","discountRate":"38","month":"03","transPrice":"1,180,000","aplySysId":"1321347387575","floor":"L","type":"A","plan":"3133","pricePerArea":"1,947 / 20,959"},{"estPropertyType":"2","saleableFloorArea":"645 / 60","discountRate":"38","month":"07","transPrice":"1,680,000","aplySysId":"1321347387575","floor":"M","type":"A","plan":"3133","pricePerArea":"2,606 / 28,047"}],"year":"2009"},{"data":[{"estPropertyType":"2","saleableFloorArea":"433 / 40","discountRate":"44","month":"04","transPrice":"1,068,000","aplySysId":"1321347387575","floor":"H","type":"A","plan":"3133","pricePerArea":"2,468 / 26,567"},{"estPropertyType":"2","saleableFloorArea":"546 / 51","discountRate":"38","month":"06","transPrice":"1,200,000","aplySysId":"1321347387575","floor":"M","type":"A","plan":"3133","pricePerArea":"2,199 / 23,669"},{"estPropertyType":"2","saleableFloorArea":"603 / 56","discountRate":"38","month":"11","transPrice":"1,380,000","aplySysId":"1321347387575","floor":"M","type":"A","plan":"3133","pricePerArea":"2,289 / 24,643"},{"estPropertyType":"2","saleableFloorArea":"603 / 56","discountRate":"38","month":"01","transPrice":"1,493,000","aplySysId":"1321347387575","floor":"M","type":"A","plan":"3133","pricePerArea":"2,477 / 26,661"},{"estPropertyType":"2","saleableFloorArea":"645 / 60","discountRate":"41","month":"08","transPrice":"1,400,000","aplySysId":"1321347387575","floor":"M","type":"A","plan":"3133","pricePerArea":"2,171 / 23,372"},{"estPropertyType":"2","saleableFloorArea":"649 / 60","discountRate":"38","month":"04","transPrice":"1,610,000","aplySysId":"1321347387575","floor":"M","type":"A","plan":"3133","pricePerArea":"2,480 / 26,700"}],"year":"2008"},{"data":[{"estPropertyType":"2","saleableFloorArea":"433 / 40","discountRate":"41","month":"05","transPrice":"700,000","aplySysId":"1321347387575","floor":"H","type":"A","plan":"3133","pricePerArea":"1,618 / 17,413"},{"estPropertyType":"2","saleableFloorArea":"438 / 41","discountRate":"41","month":"07","transPrice":"738,000","aplySysId":"1321347387575","floor":"M","type":"A","plan":"3133","pricePerArea":"1,685 / 18,133"},{"estPropertyType":"2","saleableFloorArea":"438 / 41","discountRate":"44","month":"09","transPrice":"550,000","aplySysId":"1321347387575","floor":"L","type":"A","plan":"3133","pricePerArea":"1,255 / 13,514"},{"estPropertyType":"2","saleableFloorArea":"538 / 50","discountRate":"41","month":"03","transPrice":"1,160,000","aplySysId":"1321347387575","floor":"H","type":"A","plan":"3133","pricePerArea":"2,155 / 23,200"},{"estPropertyType":"2","saleableFloorArea":"538 / 50","discountRate":"38","month":"06","transPrice":"950,000","aplySysId":"1321347387575","floor":"H","type":"S","plan":"3133","pricePerArea":"1,765 / 19,000"},{"estPropertyType":"2","saleableFloorArea":"541 / 50","discountRate":"38","month":"07","transPrice":"860,000","aplySysId":"1321347387575","floor":"M","type":"A","plan":"3133","pricePerArea":"1,588 / 17,097"},{"estPropertyType":"2","saleableFloorArea":"541 / 50","discountRate":"38","month":"01","transPrice":"960,000","aplySysId":"1321347387575","floor":"M","type":"A","plan":"3133","pricePerArea":"1,773 / 19,085"},{"estPropertyType":"2","saleableFloorArea":"541 / 50","discountRate":"38","month":"11","transPrice":"788,000","aplySysId":"1321347387575","floor":"M","type":"A","plan":"3133","pricePerArea":"1,455 / 15,666"},{"estPropertyType":"2","saleableFloorArea":"541 / 50","discountRate":"38","month":"10","transPrice":"945,000","aplySysId":"1321347387575","floor":"M","type":"A","plan":"3133","pricePerArea":"1,745 / 18,787"},{"estPropertyType":"2","saleableFloorArea":"546 / 51","discountRate":"38","month":"04","transPrice":"938,000","aplySysId":"1321347387575","floor":"L","type":"A","plan":"3133","pricePerArea":"1,719 / 18,501"},{"estPropertyType":"2","saleableFloorArea":"546 / 51","discountRate":"38","month":"06","transPrice":"960,000","aplySysId":"1321347387575","floor":"M","type":"A","plan":"3133","pricePerArea":"1,759 / 18,935"},{"estPropertyType":"2","saleableFloorArea":"546 / 51","discountRate":"38","month":"07","transPrice":"850,000","aplySysId":"1321347387575","floor":"M","type":"A","plan":"3133","pricePerArea":"1,558 / 16,765"},{"estPropertyType":"2","saleableFloorArea":"546 / 51","discountRate":"41","month":"06","transPrice":"1,000,000","aplySysId":"1321347387575","floor":"L","type":"S","plan":"3133","pricePerArea":"1,832 / 19,724"},{"estPropertyType":"2","saleableFloorArea":"546 / 51","discountRate":"41","month":"01","transPrice":"888,000","aplySysId":"1321347387575","floor":"L","type":"A","plan":"3133","pricePerArea":"1,627 / 17,515"},{"estPropertyType":"2","saleableFloorArea":"598 / 56","discountRate":"38","month":"08","transPrice":"1,000,000","aplySysId":"1321347387575","floor":"H","type":"A","plan":"3133","pricePerArea":"1,671 / 17,986"},{"estPropertyType":"2","saleableFloorArea":"598 / 56","discountRate":"38","month":"07","transPrice":"980,000","aplySysId":"1321347387575","floor":"H","type":"A","plan":"3133","pricePerArea":"1,637 / 17,626"},{"estPropertyType":"2","saleableFloorArea":"598 / 56","discountRate":"41","month":"08","transPrice":"1,350,000","aplySysId":"1321347387575","floor":"H","type":"A","plan":"3133","pricePerArea":"2,256 / 24,281"},{"estPropertyType":"2","saleableFloorArea":"603 / 56","discountRate":"41","month":"04","transPrice":"1,380,000","aplySysId":"1321347387575","floor":"H","type":"A","plan":"3133","pricePerArea":"2,289 / 24,643"},{"estPropertyType":"2","saleableFloorArea":"606 / 56","discountRate":"38","month":"04","transPrice":"1,200,000","aplySysId":"1321347387575","floor":"M","type":"A","plan":"3133","pricePerArea":"1,980 / 21,314"},{"estPropertyType":"2","saleableFloorArea":"606 / 56","discountRate":"41","month":"11","transPrice":"780,000","aplySysId":"1321347387575","floor":"L","type":"A","plan":"3133","pricePerArea":"1,287 / 13,854"},{"estPropertyType":"2","saleableFloorArea":"640 / 60","discountRate":"38","month":"07","transPrice":"1,210,000","aplySysId":"1321347387575","floor":"H","type":"A","plan":"3133","pricePerArea":"1,889 / 20,336"},{"estPropertyType":"2","saleableFloorArea":"649 / 60","discountRate":"38","month":"09","transPrice":"1,080,000","aplySysId":"1321347387575","floor":"L","type":"A","plan":"3133","pricePerArea":"1,664 / 17,910"}],"year":"2002"},{"data":[{"estPropertyType":"2","saleableFloorArea":"433 / 40","discountRate":"44","month":"12","transPrice":"3,980,000","aplySysId":"1321347387575","floor":"H","type":"A","plan":"3133","pricePerArea":"9,198 / 99,005"},{"estPropertyType":"2","saleableFloorArea":"546 / 51","discountRate":"38","month":"10","transPrice":"4,150,000","aplySysId":"1321347387575","floor":"L","type":"A","plan":"3133","pricePerArea":"7,604 / 81,854"},{"estPropertyType":"2","saleableFloorArea":"546 / 51","discountRate":"41","month":"03","transPrice":"4,720,000","aplySysId":"1321347387575","floor":"M","type":"A","plan":"3133","pricePerArea":"8,649 / 93,097"},{"estPropertyType":"2","saleableFloorArea":"546 / 51","discountRate":"41","month":"01","transPrice":"4,080,000","aplySysId":"1321347387575","floor":"L","type":"A","plan":"3133","pricePerArea":"7,476 / 80,473"},{"estPropertyType":"2","saleableFloorArea":"598 / 56","discountRate":"41","month":"03","transPrice":"4,500,000","aplySysId":"1321347387575","floor":"H","type":"A","plan":"3133","pricePerArea":"7,519 / 80,935"},{"estPropertyType":"2","saleableFloorArea":"598 / 56","discountRate":"38","month":"04","transPrice":"5,650,000","aplySysId":"1321347387575","floor":"H","type":"A","plan":"3133","pricePerArea":"9,441 / 101,619"},{"estPropertyType":"2","saleableFloorArea":"598 / 56","discountRate":"38","month":"12","transPrice":"5,650,000","aplySysId":"1321347387575","floor":"H","type":"A","plan":"3133","pricePerArea":"9,441 / 101,619"},{"estPropertyType":"2","saleableFloorArea":"603 / 56","discountRate":"41","month":"05","transPrice":"5,580,000","aplySysId":"1321347387575","floor":"M","type":"A","plan":"3133","pricePerArea":"9,257 / 99,643"},{"estPropertyType":"2","saleableFloorArea":"606 / 56","discountRate":"41","month":"06","transPrice":"5,400,000","aplySysId":"1321347387575","floor":"L","type":"A","plan":"3133","pricePerArea":"8,911 / 95,915"},{"estPropertyType":"2","saleableFloorArea":"606 / 56","discountRate":"41","month":"02","transPrice":"4,450,000","aplySysId":"1321347387575","floor":"L","type":"A","plan":"3133","pricePerArea":"7,343 / 79,041"},{"estPropertyType":"2","saleableFloorArea":"640 / 60","discountRate":"41","month":"09","transPrice":"4,800,000","aplySysId":"1321347387575","floor":"H","type":"A","plan":"3133","pricePerArea":"7,495 / 80,672"}],"year":"2019"},{"data":[{"estPropertyType":"2","saleableFloorArea":"433 / 40","discountRate":"41","month":"01","transPrice":"2,780,000","aplySysId":"1321347387575","floor":"H","type":"A","plan":"3133","pricePerArea":"6,425 / 69,154"},{"estPropertyType":"2","saleableFloorArea":"541 / 50","discountRate":"38","month":"01","transPrice":"2,580,000","aplySysId":"1321347387575","floor":"H","type":"A","plan":"3133","pricePerArea":"4,765 / 51,292"},{"estPropertyType":"2","saleableFloorArea":"546 / 51","discountRate":"38","month":"06","transPrice":"3,200,000","aplySysId":"1321347387575","floor":"L","type":"A","plan":"3133","pricePerArea":"5,864 / 63,116"},{"estPropertyType":"2","saleableFloorArea":"598 / 56","discountRate":"38","month":"02","transPrice":"3,800,000","aplySysId":"1321347387575","floor":"H","type":"A","plan":"3133","pricePerArea":"6,349 / 68,345"},{"estPropertyType":"2","saleableFloorArea":"598 / 56","discountRate":"38","month":"05","transPrice":"3,950,000","aplySysId":"1321347387575","floor":"H","type":"A","plan":"3133","pricePerArea":"6,600 / 71,043"},{"estPropertyType":"2","saleableFloorArea":"603 / 56","discountRate":"41","month":"08","transPrice":"4,600,000","aplySysId":"1321347387575","floor":"M","type":"A","plan":"3133","pricePerArea":"7,631 / 82,143"},{"estPropertyType":"2","saleableFloorArea":"606 / 56","discountRate":"38","month":"10","transPrice":"4,300,000","aplySysId":"1321347387575","floor":"L","type":"A","plan":"3133","pricePerArea":"7,096 / 76,377"},{"estPropertyType":"2","saleableFloorArea":"606 / 56","discountRate":"38","month":"01","transPrice":"3,900,000","aplySysId":"1321347387575","floor":"M","type":"A","plan":"3133","pricePerArea":"6,436 / 69,272"},{"estPropertyType":"2","saleableFloorArea":"606 / 56","discountRate":"41","month":"11","transPrice":"2,930,000","aplySysId":"1321347387575","floor":"L","type":"A","plan":"3133","pricePerArea":"4,835 / 52,043"},{"estPropertyType":"2","saleableFloorArea":"645 / 60","discountRate":"38","month":"05","transPrice":"4,000,000","aplySysId":"1321347387575","floor":"M","type":"A","plan":"3133","pricePerArea":"6,204 / 66,778"},{"estPropertyType":"2","saleableFloorArea":"649 / 60","discountRate":"41","month":"06","transPrice":"4,600,000","aplySysId":"1321347387575","floor":"L","type":"A","plan":"3133","pricePerArea":"7,087 / 76,285"}],"year":"2015"},{"data":[{"estPropertyType":"2","saleableFloorArea":"435 / 40","discountRate":"38","month":"03","transPrice":"2,550,000","aplySysId":"1321347387575","floor":"M","type":"A","plan":"3133","pricePerArea":"5,864 / 63,119"},{"estPropertyType":"2","saleableFloorArea":"438 / 41","discountRate":"38","month":"09","transPrice":"2,680,000","aplySysId":"1321347387575","floor":"L","type":"A","plan":"3133","pricePerArea":"6,117 / 65,848"},{"estPropertyType":"2","saleableFloorArea":"538 / 50","discountRate":"41","month":"08","transPrice":"2,940,000","aplySysId":"1321347387575","floor":"H","type":"A","plan":"3133","pricePerArea":"5,463 / 58,800"},{"estPropertyType":"2","saleableFloorArea":"538 / 50","discountRate":"38","month":"02","transPrice":"3,000,000","aplySysId":"1321347387575","floor":"H","type":"A","plan":"3133","pricePerArea":"5,574 / 60,000"},{"estPropertyType":"2","saleableFloorArea":"538 / 50","discountRate":"38","month":"06","transPrice":"2,900,000","aplySysId":"1321347387575","floor":"H","type":"A","plan":"3133","pricePerArea":"5,388 / 58,000"},{"estPropertyType":"2","saleableFloorArea":"541 / 50","discountRate":"38","month":"07","transPrice":"2,850,000","aplySysId":"1321347387575","floor":"M","type":"A","plan":"3133","pricePerArea":"5,264 / 56,660"},{"estPropertyType":"2","saleableFloorArea":"541 / 50","discountRate":"38","month":"04","transPrice":"2,900,000","aplySysId":"1321347387575","floor":"H","type":"A","plan":"3133","pricePerArea":"5,356 / 57,654"},{"estPropertyType":"2","saleableFloorArea":"541 / 50","discountRate":"38","month":"12","transPrice":"2,950,000","aplySysId":"1321347387575","floor":"M","type":"A","plan":"3133","pricePerArea":"5,449 / 58,648"},{"estPropertyType":"2","saleableFloorArea":"546 / 51","discountRate":"38","month":"05","transPrice":"2,668,000","aplySysId":"1321347387575","floor":"L","type":"A","plan":"3133","pricePerArea":"4,889 / 52,623"},{"estPropertyType":"2","saleableFloorArea":"546 / 51","discountRate":"38","month":"12","transPrice":"3,050,000","aplySysId":"1321347387575","floor":"L","type":"A","plan":"3133","pricePerArea":"5,589 / 60,158"},{"estPropertyType":"2","saleableFloorArea":"598 / 56","discountRate":"41","month":"09","transPrice":"3,380,000","aplySysId":"1321347387575","floor":"H","type":"A","plan":"3133","pricePerArea":"5,648 / 60,791"},{"estPropertyType":"2","saleableFloorArea":"598 / 56","discountRate":"41","month":"06","transPrice":"3,980,000","aplySysId":"1321347387575","floor":"H","type":"A","plan":"3133","pricePerArea":"6,650 / 71,583"},{"estPropertyType":"2","saleableFloorArea":"603 / 56","discountRate":"38","month":"07","transPrice":"3,670,000","aplySysId":"1321347387575","floor":"M","type":"A","plan":"3133","pricePerArea":"6,088 / 65,536"},{"estPropertyType":"2","saleableFloorArea":"603 / 56","discountRate":"41","month":"02","transPrice":"3,360,000","aplySysId":"1321347387575","floor":"M","type":"A","plan":"3133","pricePerArea":"5,574 / 60,000"},{"estPropertyType":"2","saleableFloorArea":"603 / 56","discountRate":"38","month":"06","transPrice":"3,120,000","aplySysId":"1321347387575","floor":"M","type":"A","plan":"3133","pricePerArea":"5,176 / 55,714"},{"estPropertyType":"2","saleableFloorArea":"606 / 56","discountRate":"38","month":"04","transPrice":"3,380,000","aplySysId":"1321347387575","floor":"L","type":"A","plan":"3133","pricePerArea":"5,577 / 60,036"},{"estPropertyType":"2","saleableFloorArea":"606 / 56","discountRate":"41","month":"05","transPrice":"3,518,000","aplySysId":"1321347387575","floor":"L","type":"A","plan":"3133","pricePerArea":"5,805 / 62,487"},{"estPropertyType":"2","saleableFloorArea":"640 / 60","discountRate":"38","month":"04","transPrice":"3,450,000","aplySysId":"1321347387575","floor":"H","type":"A","plan":"3133","pricePerArea":"5,387 / 57,983"},{"estPropertyType":"2","saleableFloorArea":"645 / 60","discountRate":"38","month":"06","transPrice":"3,420,000","aplySysId":"1321347387575","floor":"H","type":"A","plan":"3133","pricePerArea":"5,304 / 57,095"},{"estPropertyType":"2","saleableFloorArea":"645 / 60","discountRate":"41","month":"12","transPrice":"3,800,000","aplySysId":"1321347387575","floor":"M","type":"S","plan":"3133","pricePerArea":"5,894 / 63,439"},{"estPropertyType":"2","saleableFloorArea":"645 / 60","discountRate":"38","month":"07","transPrice":"3,580,000","aplySysId":"1321347387575","floor":"M","type":"A","plan":"3133","pricePerArea":"5,552 / 59,766"},{"estPropertyType":"2","saleableFloorArea":"649 / 60","discountRate":"38","month":"03","transPrice":"3,100,000","aplySysId":"1321347387575","floor":"L","type":"A","plan":"3133","pricePerArea":"4,776 / 51,410"}],"year":"2014"},{"data":[{"estPropertyType":"2","saleableFloorArea":"435 / 40","discountRate":"38","month":"04","transPrice":"1,380,000","aplySysId":"1321347387575","floor":"M","type":"A","plan":"3133","pricePerArea":"3,173 / 34,158"},{"estPropertyType":"2","saleableFloorArea":"541 / 50","discountRate":"38","month":"05","transPrice":"1,860,000","aplySysId":"1321347387575","floor":"M","type":"A","plan":"3133","pricePerArea":"3,435 / 36,978"},{"estPropertyType":"2","saleableFloorArea":"546 / 51","discountRate":"41","month":"10","transPrice":"1,850,000","aplySysId":"1321347387575","floor":"L","type":"A","plan":"3133","pricePerArea":"3,390 / 36,489"},{"estPropertyType":"2","saleableFloorArea":"598 / 56","discountRate":"38","month":"02","transPrice":"2,060,000","aplySysId":"1321347387575","floor":"H","type":"A","plan":"3133","pricePerArea":"3,442 / 37,050"},{"estPropertyType":"2","saleableFloorArea":"598 / 56","discountRate":"41","month":"11","transPrice":"2,330,000","aplySysId":"1321347387575","floor":"H","type":"A","plan":"3133","pricePerArea":"3,893 / 41,906"},{"estPropertyType":"2","saleableFloorArea":"603 / 56","discountRate":"41","month":"06","transPrice":"3,100,000","aplySysId":"1321347387575","floor":"M","type":"A","plan":"3133","pricePerArea":"5,143 / 55,357"},{"estPropertyType":"2","saleableFloorArea":"606 / 56","discountRate":"38","month":"02","transPrice":"1,900,000","aplySysId":"1321347387575","floor":"L","type":"A","plan":"3133","pricePerArea":"3,135 / 33,748"},{"estPropertyType":"2","saleableFloorArea":"606 / 56","discountRate":"38","month":"05","transPrice":"2,000,000","aplySysId":"1321347387575","floor":"L","type":"S","plan":"3133","pricePerArea":"3,300 / 35,524"},{"estPropertyType":"2","saleableFloorArea":"606 / 56","discountRate":"43","month":"12","transPrice":"2,250,000","aplySysId":"1321347387575","floor":"M","type":"A","plan":"3133","pricePerArea":"3,713 / 39,964"},{"estPropertyType":"2","saleableFloorArea":"640 / 60","discountRate":"41","month":"07","transPrice":"2,000,000","aplySysId":"1321347387575","floor":"H","type":"A","plan":"3133","pricePerArea":"3,123 / 33,613"},{"estPropertyType":"2","saleableFloorArea":"649 / 60","discountRate":"38","month":"10","transPrice":"2,290,000","aplySysId":"1321347387575","floor":"L","type":"A","plan":"3133","pricePerArea":"3,528 / 37,977"},{"estPropertyType":"2","saleableFloorArea":"649 / 60","discountRate":"38","month":"06","transPrice":"2,350,000","aplySysId":"1321347387575","floor":"L","type":"A","plan":"3133","pricePerArea":"3,621 / 38,972"},{"estPropertyType":"2","saleableFloorArea":"649 / 60","discountRate":"41","month":"04","transPrice":"2,390,000","aplySysId":"1321347387575","floor":"M","type":"A","plan":"3133","pricePerArea":"3,682 / 39,635"}],"year":"2011"},{"data":[{"estPropertyType":"2","saleableFloorArea":"438 / 41","discountRate":"44","month":"03","transPrice":"650,000","aplySysId":"1321347387575","floor":"L","type":"A","plan":"3133","pricePerArea":"1,484 / 15,971"},{"estPropertyType":"2","saleableFloorArea":"538 / 50","discountRate":"41","month":"09","transPrice":"1,330,000","aplySysId":"1321347387575","floor":"H","type":"A","plan":"3133","pricePerArea":"2,471 / 26,600"},{"estPropertyType":"2","saleableFloorArea":"538 / 50","discountRate":"41","month":"11","transPrice":"1,038,000","aplySysId":"1321347387575","floor":"H","type":"A","plan":"3133","pricePerArea":"1,929 / 20,760"},{"estPropertyType":"2","saleableFloorArea":"541 / 50","discountRate":"38","month":"10","transPrice":"932,000","aplySysId":"1321347387575","floor":"M","type":"A","plan":"3133","pricePerArea":"1,721 / 18,529"},{"estPropertyType":"2","saleableFloorArea":"541 / 50","discountRate":"38","month":"01","transPrice":"1,000,000","aplySysId":"1321347387575","floor":"M","type":"S","plan":"3133","pricePerArea":"1,847 / 19,881"},{"estPropertyType":"2","saleableFloorArea":"541 / 50","discountRate":"38","month":"01","transPrice":"1,092,000","aplySysId":"1321347387575","floor":"M","type":"A","plan":"3133","pricePerArea":"2,017 / 21,710"},{"estPropertyType":"2","saleableFloorArea":"598 / 56","discountRate":"38","month":"08","transPrice":"1,280,000","aplySysId":"1321347387575","floor":"H","type":"A","plan":"3133","pricePerArea":"2,139 / 23,022"},{"estPropertyType":"2","saleableFloorArea":"603 / 56","discountRate":"38","month":"05","transPrice":"1,300,000","aplySysId":"1321347387575","floor":"M","type":"A","plan":"3133","pricePerArea":"2,157 / 23,214"},{"estPropertyType":"2","saleableFloorArea":"603 / 56","discountRate":"38","month":"07","transPrice":"1,338,000","aplySysId":"1321347387575","floor":"M","type":"A","plan":"3133","pricePerArea":"2,220 / 23,893"},{"estPropertyType":"2","saleableFloorArea":"606 / 56","discountRate":"38","month":"09","transPrice":"1,400,000","aplySysId":"1321347387575","floor":"L","type":"A","plan":"3133","pricePerArea":"2,310 / 24,867"},{"estPropertyType":"2","saleableFloorArea":"640 / 60","discountRate":"41","month":"03","transPrice":"1,600,000","aplySysId":"1321347387575","floor":"H","type":"A","plan":"3133","pricePerArea":"2,498 / 26,891"},{"estPropertyType":"2","saleableFloorArea":"645 / 60","discountRate":"38","month":"10","transPrice":"1,300,000","aplySysId":"1321347387575","floor":"M","type":"A","plan":"3133","pricePerArea":"2,016 / 21,703"},{"estPropertyType":"2","saleableFloorArea":"645 / 60","discountRate":"38","month":"02","transPrice":"1,248,000","aplySysId":"1321347387575","floor":"M","type":"A","plan":"3133","pricePerArea":"1,936 / 20,835"},{"estPropertyType":"2","saleableFloorArea":"921 / 86","discountRate":"38","month":"05","transPrice":"1,450,000","aplySysId":"1321347387575","floor":"H","type":"A","plan":"3133","pricePerArea":"1,574 / 16,939"}],"year":"2005"},{"data":[{"estPropertyType":"2","saleableFloorArea":"538 / 50","discountRate":"38","month":"11","transPrice":"1,960,000","aplySysId":"1321347387575","floor":"H","type":"A","plan":"3133","pricePerArea":"3,642 / 39,200"},{"estPropertyType":"2","saleableFloorArea":"538 / 50","discountRate":"38","month":"05","transPrice":"1,408,000","aplySysId":"1321347387575","floor":"H","type":"A","plan":"3133","pricePerArea":"2,616 / 28,160"},{"estPropertyType":"2","saleableFloorArea":"541 / 50","discountRate":"38","month":"09","transPrice":"1,530,000","aplySysId":"1321347387575","floor":"M","type":"A","plan":"3133","pricePerArea":"2,826 / 30,417"},{"estPropertyType":"2","saleableFloorArea":"541 / 50","discountRate":"41","month":"08","transPrice":"1,980,000","aplySysId":"1321347387575","floor":"M","type":"A","plan":"3133","pricePerArea":"3,657 / 39,364"},{"estPropertyType":"2","saleableFloorArea":"598 / 56","discountRate":"41","month":"10","transPrice":"2,550,000","aplySysId":"1321347387575","floor":"H","type":"A","plan":"3133","pricePerArea":"4,261 / 45,863"},{"estPropertyType":"2","saleableFloorArea":"598 / 56","discountRate":"38","month":"11","transPrice":"2,250,000","aplySysId":"1321347387575","floor":"H","type":"A","plan":"3133","pricePerArea":"3,760 / 40,468"},{"estPropertyType":"2","saleableFloorArea":"603 / 56","discountRate":"41","month":"10","transPrice":"2,000,000","aplySysId":"1321347387575","floor":"M","type":"S","plan":"3133","pricePerArea":"3,318 / 35,714"},{"estPropertyType":"2","saleableFloorArea":"603 / 56","discountRate":"38","month":"11","transPrice":"2,100,000","aplySysId":"1321347387575","floor":"M","type":"A","plan":"3133","pricePerArea":"3,484 / 37,500"},{"estPropertyType":"2","saleableFloorArea":"606 / 56","discountRate":"38","month":"07","transPrice":"1,920,000","aplySysId":"1321347387575","floor":"L","type":"A","plan":"3133","pricePerArea":"3,168 / 34,103"},{"estPropertyType":"2","saleableFloorArea":"606 / 56","discountRate":"38","month":"01","transPrice":"1,850,000","aplySysId":"1321347387575","floor":"L","type":"A","plan":"3133","pricePerArea":"3,053 / 32,860"},{"estPropertyType":"2","saleableFloorArea":"645 / 60","discountRate":"44","month":"12","transPrice":"1,870,000","aplySysId":"1321347387575","floor":"M","type":"A","plan":"3133","pricePerArea":"2,900 / 31,219"},{"estPropertyType":"2","saleableFloorArea":"645 / 60","discountRate":"41","month":"03","transPrice":"1,730,000","aplySysId":"1321347387575","floor":"M","type":"A","plan":"3133","pricePerArea":"2,683 / 28,881"},{"estPropertyType":"2","saleableFloorArea":"649 / 60","discountRate":"41","month":"05","transPrice":"1,700,000","aplySysId":"1321347387575","floor":"L","type":"A","plan":"3133","pricePerArea":"2,619 / 28,192"}],"year":"2010"},{"data":[{"estPropertyType":"2","saleableFloorArea":"538 / 50","discountRate":"41","month":"06","transPrice":"1,173,000","aplySysId":"1321347387575","floor":"H","type":"A","plan":"3133","pricePerArea":"2,179 / 23,460"},{"estPropertyType":"2","saleableFloorArea":"541 / 50","discountRate":"38","month":"11","transPrice":"1,073,000","aplySysId":"1321347387575","floor":"H","type":"A","plan":"3133","pricePerArea":"1,982 / 21,332"},{"estPropertyType":"2","saleableFloorArea":"541 / 50","discountRate":"38","month":"08","transPrice":"1,180,000","aplySysId":"1321347387575","floor":"M","type":"A","plan":"3133","pricePerArea":"2,179 / 23,459"},{"estPropertyType":"2","saleableFloorArea":"541 / 50","discountRate":"41","month":"05","transPrice":"1,180,000","aplySysId":"1321347387575","floor":"M","type":"A","plan":"3133","pricePerArea":"2,179 / 23,459"},{"estPropertyType":"2","saleableFloorArea":"546 / 51","discountRate":"41","month":"06","transPrice":"950,000","aplySysId":"1321347387575","floor":"M","type":"A","plan":"3133","pricePerArea":"1,741 / 18,738"},{"estPropertyType":"2","saleableFloorArea":"546 / 51","discountRate":"38","month":"08","transPrice":"1,120,000","aplySysId":"1321347387575","floor":"M","type":"A","plan":"3133","pricePerArea":"2,052 / 22,091"},{"estPropertyType":"2","saleableFloorArea":"546 / 51","discountRate":"38","month":"10","transPrice":"1,000,000","aplySysId":"1321347387575","floor":"L","type":"A","plan":"3133","pricePerArea":"1,832 / 19,724"},{"estPropertyType":"2","saleableFloorArea":"546 / 51","discountRate":"38","month":"03","transPrice":"960,000","aplySysId":"1321347387575","floor":"L","type":"A","plan":"3133","pricePerArea":"1,759 / 18,935"},{"estPropertyType":"2","saleableFloorArea":"546 / 51","discountRate":"38","month":"04","transPrice":"938,000","aplySysId":"1321347387575","floor":"M","type":"A","plan":"3133","pricePerArea":"1,719 / 18,501"},{"estPropertyType":"2","saleableFloorArea":"546 / 51","discountRate":"41","month":"08","transPrice":"1,030,000","aplySysId":"1321347387575","floor":"L","type":"A","plan":"3133","pricePerArea":"1,887 / 20,316"},{"estPropertyType":"2","saleableFloorArea":"546 / 51","discountRate":"38","month":"01","transPrice":"920,000","aplySysId":"1321347387575","floor":"L","type":"A","plan":"3133","pricePerArea":"1,686 / 18,146"},{"estPropertyType":"2","saleableFloorArea":"598 / 56","discountRate":"41","month":"09","transPrice":"1,630,000","aplySysId":"1321347387575","floor":"H","type":"A","plan":"3133","pricePerArea":"2,724 / 29,317"},{"estPropertyType":"2","saleableFloorArea":"603 / 56","discountRate":"38","month":"10","transPrice":"1,380,000","aplySysId":"1321347387575","floor":"M","type":"A","plan":"3133","pricePerArea":"2,289 / 24,643"},{"estPropertyType":"2","saleableFloorArea":"603 / 56","discountRate":"38","month":"11","transPrice":"1,350,000","aplySysId":"1321347387575","floor":"M","type":"A","plan":"3133","pricePerArea":"2,240 / 24,107"},{"estPropertyType":"2","saleableFloorArea":"606 / 56","discountRate":"38","month":"04","transPrice":"1,080,000","aplySysId":"1321347387575","floor":"L","type":"A","plan":"3133","pricePerArea":"1,782 / 19,183"},{"estPropertyType":"2","saleableFloorArea":"640 / 60","discountRate":"38","month":"08","transPrice":"1,710,000","aplySysId":"1321347387575","floor":"H","type":"A","plan":"3133","pricePerArea":"2,670 / 28,739"},{"estPropertyType":"2","saleableFloorArea":"649 / 60","discountRate":"38","month":"01","transPrice":"1,350,000","aplySysId":"1321347387575","floor":"L","type":"A","plan":"3133","pricePerArea":"2,080 / 22,388"}],"year":"2007"},{"data":[{"estPropertyType":"2","saleableFloorArea":"541 / 50","discountRate":"38","month":"09","transPrice":"1,176,800","aplySysId":"1321347387575","floor":"M","type":"A","plan":"3133","pricePerArea":"2,174 / 23,396"},{"estPropertyType":"2","saleableFloorArea":"541 / 50","discountRate":"41","month":"02","transPrice":"1,080,000","aplySysId":"1321347387575","floor":"M","type":"A","plan":"3133","pricePerArea":"1,995 / 21,471"},{"estPropertyType":"2","saleableFloorArea":"541 / 50","discountRate":"41","month":"12","transPrice":"1,110,000","aplySysId":"1321347387575","floor":"M","type":"A","plan":"3133","pricePerArea":"2,050 / 22,068"},{"estPropertyType":"2","saleableFloorArea":"546 / 51","discountRate":"38","month":"09","transPrice":"950,000","aplySysId":"1321347387575","floor":"L","type":"A","plan":"3133","pricePerArea":"1,741 / 18,738"},{"estPropertyType":"2","saleableFloorArea":"598 / 56","discountRate":"38","month":"07","transPrice":"1,188,000","aplySysId":"1321347387575","floor":"H","type":"A","plan":"3133","pricePerArea":"1,985 / 21,367"},{"estPropertyType":"2","saleableFloorArea":"598 / 56","discountRate":"41","month":"10","transPrice":"1,500,000","aplySysId":"1321347387575","floor":"H","type":"A","plan":"3133","pricePerArea":"2,506 / 26,978"},{"estPropertyType":"2","saleableFloorArea":"598 / 56","discountRate":"38","month":"10","transPrice":"1,168,000","aplySysId":"1321347387575","floor":"H","type":"A","plan":"3133","pricePerArea":"1,952 / 21,007"},{"estPropertyType":"2","saleableFloorArea":"598 / 56","discountRate":"41","month":"08","transPrice":"1,750,000","aplySysId":"1321347387575","floor":"H","type":"A","plan":"3133","pricePerArea":"2,924 / 31,475"},{"estPropertyType":"2","saleableFloorArea":"603 / 56","discountRate":"41","month":"08","transPrice":"1,550,000","aplySysId":"1321347387575","floor":"M","type":"A","plan":"3133","pricePerArea":"2,571 / 27,679"},{"estPropertyType":"2","saleableFloorArea":"606 / 56","discountRate":"41","month":"12","transPrice":"1,500,000","aplySysId":"1321347387575","floor":"M","type":"A","plan":"3133","pricePerArea":"2,475 / 26,643"},{"estPropertyType":"2","saleableFloorArea":"640 / 60","discountRate":"38","month":"02","transPrice":"1,260,000","aplySysId":"1321347387575","floor":"H","type":"A","plan":"3133","pricePerArea":"1,967 / 21,176"},{"estPropertyType":"2","saleableFloorArea":"645 / 60","discountRate":"38","month":"12","transPrice":"1,288,000","aplySysId":"1321347387575","floor":"H","type":"A","plan":"3133","pricePerArea":"1,998 / 21,503"},{"estPropertyType":"2","saleableFloorArea":"645 / 60","discountRate":"38","month":"06","transPrice":"1,280,000","aplySysId":"1321347387575","floor":"M","type":"A","plan":"3133","pricePerArea":"1,985 / 21,369"},{"estPropertyType":"2","saleableFloorArea":"649 / 60","discountRate":"38","month":"12","transPrice":"1,485,000","aplySysId":"1321347387575","floor":"L","type":"A","plan":"3133","pricePerArea":"2,288 / 24,627"}],"year":"2006"}],"courtAndEstate":{"zh-Hans":"","zh-Hant":"","en":"Hong Nga Court"},"district":{"zh-Hans":"","zh-Hant":"","en":"Kwun Tong"},"location":{"zh-Hans":"","zh-Hant":"","en":"Lam Tin"},"aplySysId":"1321347387575","region":{"zh-Hans":"","zh-Hant":"","en":"Kowloon"}}